yuca/__init__.py
yuca/app_data.py
yuca/data_handlers.py
yuca/generation.py
yuca/main.py
yuca/template/__init__.py
yuca/template/template_app.py
yuca/warehouse/__init__.py
yuca/warehouse/example_user_data.yml
yuca/warehouse/warehouse_app.py
yuca-0.1.0.dist-info/LICENSE
yuca-0.1.0.dist-info/METADATA
yuca-0.1.0.dist-info/WHEEL
yuca-0.1.0.dist-info/entry_points.txt
yuca-0.1.0.dist-info/top_level.txt
yuca-0.1.0.dist-info/RECORD
