Metadata-Version: 2.1
Name: yuca
Version: 0.1.0
Summary: CLI tool for fast personal data processing and visualization
Author-email: Jorge Morgado Vega <jorge.morgadov@gmail.com>, Gustavo Viera-López <gvieralopez@gmail.com>
License: MIT License
Project-URL: Homepage, https://github.com/yuca-devs/yuca
Keywords: tremplate handler,cv generator
Classifier: License :: OSI Approved :: MIT License
Classifier: Programming Language :: Python
Classifier: Programming Language :: Python :: 3
Requires-Python: >=3.10
License-File: LICENSE
Requires-Dist: GitPython >=3.1.31
Requires-Dist: typer >=0.9.0
Requires-Dist: ruamel-yaml >=0.17.32
Requires-Dist: jinja2 >=3.1.2
Requires-Dist: platformdirs >=3.10.0
Requires-Dist: typing-extensions >=4.7.1
Provides-Extra: dev
Requires-Dist: mypy ; extra == 'dev'
Requires-Dist: black ; extra == 'dev'
Requires-Dist: pylint ; extra == 'dev'
Requires-Dist: bumpver ; extra == 'dev'
Requires-Dist: isort ; extra == 'dev'
Requires-Dist: pytest ; extra == 'dev'
